README.rst
remove_backups.py
setup.py
remove_backups.egg-info/PKG-INFO
remove_backups.egg-info/SOURCES.txt
remove_backups.egg-info/dependency_links.txt
remove_backups.egg-info/not-zip-safe
remove_backups.egg-info/top_level.txt